src/example_etl/__init__.py
src/example_etl/app.py
src/example_etl/cmdline.py
src/example_etl/config/__init__.py
src/example_etl/config/config.py
src/example_etl/config/settings.yml
src/example_etl/log.py
liyedong_example_etl-0.1.0.dist-info/entry_points.txt
liyedong_example_etl-0.1.0.dist-info/LICENSE
liyedong_example_etl-0.1.0.dist-info/METADATA
liyedong_example_etl-0.1.0.dist-info/WHEEL
liyedong_example_etl-0.1.0.dist-info/RECORD
