Metadata-Version: 2.1
Name: liyedong_example_etl
Version: 0.1.0
Summary: This is my first etl project.
License: MIT
Author: test
Author-email: test@example.com
Requires-Python: >=3.11,<4.0
Classifier: License :: OSI Approved :: MIT License
Classifier: Operating System :: OS Independent
Classifier: Programming Language :: Python :: 3
Classifier: Programming Language :: Python :: 3.11
Classifier: Programming Language :: Python :: 3.12
Requires-Dist: click (>=8.1.3,<9.0.0)
Requires-Dist: dynaconf (>=3.1.12,<4.0.0)
